MANIFEST.in
README.rst
setup.cfg
setup.py
trionyx_invoices/__init__.py
trionyx_invoices/apps.py
trionyx_invoices/conf.py
trionyx_invoices/cron.py
trionyx_invoices/forms.py
trionyx_invoices/layouts.py
trionyx_invoices/models.py
trionyx_invoices/tasks.py
trionyx_invoices/widgets.py
trionyx_invoices.egg-info/PKG-INFO
trionyx_invoices.egg-info/SOURCES.txt
trionyx_invoices.egg-info/dependency_links.txt
trionyx_invoices.egg-info/entry_points.txt
trionyx_invoices.egg-info/requires.txt
trionyx_invoices.egg-info/top_level.txt
trionyx_invoices/locale/en_US/LC_MESSAGES/django.mo
trionyx_invoices/locale/en_US/LC_MESSAGES/django.po
trionyx_invoices/locale/nl_NL/LC_MESSAGES/django.mo
trionyx_invoices/locale/nl_NL/LC_MESSAGES/django.po
trionyx_invoices/migrations/0001_initial.py
trionyx_invoices/migrations/0002_auto_20200102_1141.py
trionyx_invoices/migrations/0003_invoicepage.py
trionyx_invoices/migrations/0004_invoice_payments_received.py
trionyx_invoices/migrations/__init__.py
trionyx_invoices/static/img/widgets/open_invoices.jpg
trionyx_invoices/templates/invoices/emails/invoice.html
trionyx_invoices/templates/invoices/emails/invoice_past_due.html
trionyx_invoices/templates/invoices/emails/invoice_reminder.html
trionyx_invoices/templates/invoices/pdf/invoice.css.html
trionyx_invoices/templates/invoices/pdf/invoice.html
trionyx_invoices/templates/widgets/open_invoices.html