Metadata-Version: 2.1
Name: trionyx-invoices
Version: 1.1.1
Summary: Trionyx app for invoices
Home-page: https://github.com/krukas/Trionyx-Invoices
Author: Maikel Martens
Author-email: maikel@martens.me
License: GPL3
Download-URL: https://github.com/krukas/Trionyx-Invoices/releases/tag/1.1.1
Keywords: Django,Trionyx,app,invoices
Platform: UNKNOWN
Classifier: License :: OSI Approved :: GNU General Public License v3 (GPLv3)
Classifier: Programming Language :: Python :: 3
Classifier: Framework :: Django
Requires-Python: ~=3.6
Provides-Extra: dev
